setup.py
qrcodegeneration/__init__.py
qrcodegeneration/script.py
qrcodegeneration.egg-info/PKG-INFO
qrcodegeneration.egg-info/SOURCES.txt
qrcodegeneration.egg-info/dependency_links.txt
qrcodegeneration.egg-info/requires.txt
qrcodegeneration.egg-info/top_level.txt