Metadata-Version: 2.1
Name: qrcodegeneration
Version: 1.0.3
Summary: Generate QR Codes!
Home-page: https://github.com/Zeroxyoutube/qrcodegeneration
Author: Zeroxyoutube
Author-email: Zeroxyoutube@gmail.com
